maix/__init__.py
maix/__init__.pyi
maix/__maix_time__.py
maix/__signal_handle__.py
maix/__signal_handle__.pyi
maix/_maix.so
maix/maix_resize.py
maix/sdv1_5.py
maix/sensevoice.py
maix/test_hardware.py
maix/version.py
maix/version.pyi
maix/_maix/__init__.pyi
maix/_maix/ahrs.pyi
maix/_maix/app.pyi
maix/_maix/audio.pyi
maix/_maix/camera.pyi
maix/_maix/display.pyi
maix/_maix/err.pyi
maix/_maix/example.pyi
maix/_maix/fs.pyi
maix/_maix/http.pyi
maix/_maix/i18n.pyi
maix/_maix/image.pyi
maix/_maix/log.pyi
maix/_maix/pipeline.pyi
maix/_maix/protocol.pyi
maix/_maix/rtmp.pyi
maix/_maix/rtsp.pyi
maix/_maix/sys.pyi
maix/_maix/tensor.pyi
maix/_maix/thread.pyi
maix/_maix/time.pyi
maix/_maix/touchscreen.pyi
maix/_maix/tracker.pyi
maix/_maix/util.pyi
maix/_maix/uvc.pyi
maix/_maix/video.pyi
maix/_maix/webrtc.pyi
maix/_maix/comm/__init__.pyi
maix/_maix/comm/modbus.pyi
maix/_maix/ext_dev/__init__.pyi
maix/_maix/ext_dev/axp2101.pyi
maix/_maix/ext_dev/bm8563.pyi
maix/_maix/ext_dev/cmap.pyi
maix/_maix/ext_dev/fp5510.pyi
maix/_maix/ext_dev/imu.pyi
maix/_maix/ext_dev/mlx90640.pyi
maix/_maix/ext_dev/pmu.pyi
maix/_maix/ext_dev/qmi8658.pyi
maix/_maix/ext_dev/tmc2209.pyi
maix/_maix/ext_dev/tof100.pyi
maix/_maix/network/__init__.pyi
maix/_maix/network/wifi.pyi
maix/_maix/nn/F.pyi
maix/_maix/nn/__init__.pyi
maix/_maix/peripheral/__init__.pyi
maix/_maix/peripheral/adc.pyi
maix/_maix/peripheral/gpio.pyi
maix/_maix/peripheral/hid.pyi
maix/_maix/peripheral/i2c.pyi
maix/_maix/peripheral/key.pyi
maix/_maix/peripheral/pinmap.pyi
maix/_maix/peripheral/pwm.pyi
maix/_maix/peripheral/spi.pyi
maix/_maix/peripheral/timer.pyi
maix/_maix/peripheral/uart.pyi
maix/_maix/peripheral/wdt.pyi
maix/v1/__init__.py
maix/v1/audio.py
maix/v1/image.py
maix/v1/lcd.py
maix/v1/sensor.py
maix/v1/video.py
maix/v1/machine/__init__.py
maix/v1/machine/uart.py
maixpy/__init__.py
maixpy-4.12.5.dist-info/licenses/LICENSE
maixpy-4.12.5.dist-info/METADATA
maixpy-4.12.5.dist-info/WHEEL
maixpy-4.12.5.dist-info/entry_points.txt
maixpy-4.12.5.dist-info/top_level.txt
maixpy-4.12.5.dist-info/RECORD
