Metadata-Version: 2.4
Name: MaixPy
Version: 4.12.5
Summary: Sipeed Maix Vision Python SDK
Home-page: https://github.com/Sipeed/MaixPy
Author: Sipeed
Author-email: support@sipeed.com
License: Apache 2.0
Keywords: Machine vision,AI vision,IOT,AIOT,Edge computing
Classifier: Development Status :: 5 - Production/Stable
Classifier: Intended Audience :: Developers
Classifier: Intended Audience :: Education
Classifier: Intended Audience :: Science/Research
Classifier: Topic :: Software Development :: Embedded Systems
Classifier: License :: OSI Approved :: Apache Software License
Classifier: Programming Language :: Python :: 3
License-File: LICENSE
Dynamic: author
Dynamic: author-email
Dynamic: classifier
Dynamic: description
Dynamic: description-content-type
Dynamic: home-page
Dynamic: keywords
Dynamic: license
Dynamic: license-file
Dynamic: summary
